bugyocloudclient/__init__.py
bugyocloudclient/__version__.py
bugyocloudclient/config.py
bugyocloudclient/core.py
bugyocloudclient/endpoints/authenticate.py
bugyocloudclient/endpoints/base/tokenpage.py
bugyocloudclient/endpoints/checkauthenticationmethod.py
bugyocloudclient/endpoints/loginpage.py
bugyocloudclient/endpoints/punchmarkpage.py
bugyocloudclient/endpoints/timeclock.py
bugyocloudclient/endpoints/toppage.py
bugyocloudclient/models/authinfo.py
bugyocloudclient/models/clientparam.py
bugyocloudclient/models/punchinfo.py
bugyocloudclient/tasks/basetask.py
bugyocloudclient/tasks/logintask.py
bugyocloudclient/tasks/punchtask.py
bugyocloudclient/utils/pagetokenparser.py
bugyocloudclient/utils/urlproducer.py
bugyocloudclient-0.3.0.dist-info/entry_points.txt
bugyocloudclient-0.3.0.dist-info/LICENSE
bugyocloudclient-0.3.0.dist-info/WHEEL
bugyocloudclient-0.3.0.dist-info/METADATA
bugyocloudclient-0.3.0.dist-info/RECORD
